FlowAPI/__init__.py
FlowAPI/admin.py
FlowAPI/automation.py
FlowAPI/cluster.py
FlowAPI/consul.py
FlowAPI/core.py
FlowAPI/daemon.py
FlowAPI/editshare.py
FlowAPI/framerate.py
FlowAPI/helmut.py
FlowAPI/ingest.py
FlowAPI/injectederrors.py
FlowAPI/mediabase.py
FlowAPI/metadata.py
FlowAPI/mirror.py
FlowAPI/mount.py
FlowAPI/multisite.py
FlowAPI/proxyworker.py
FlowAPI/qscan.py
FlowAPI/rendermaster.py
FlowAPI/scan.py
FlowAPI/scanworker.py
FlowAPI/search.py
FlowAPI/statistics.py
FlowAPI/story.py
FlowAPI/sync.py
FlowAPI/timecode.py
FlowAPI/transfer.py
FlowAPI/warp.py
FlowAPI/watchfolder.py
flowpyapi-0.1.5.dist-info/LICENSE
flowpyapi-0.1.5.dist-info/METADATA
flowpyapi-0.1.5.dist-info/WHEEL
flowpyapi-0.1.5.dist-info/top_level.txt
flowpyapi-0.1.5.dist-info/RECORD
