Metadata-Version: 2.1
Name: flowpyapi
Version: 0.1.5
Summary: FLOW Python API
Home-page: https://www.editshare.com
Author: EditShare
Author-email: editshare-api@editshare.com
Classifier: Programming Language :: Python :: 3
Classifier: License :: OSI Approved :: MIT License
Classifier: Operating System :: OS Independent
Requires-Python: >=3.6
License-File: LICENSE
